consul/__init__.py
consul/aio.py
consul/base.py
consul/std.py
consul/tornado.py
consul/twisted.py
python_consul2-0.1.5.dist-info/LICENSE
python_consul2-0.1.5.dist-info/METADATA
python_consul2-0.1.5.dist-info/WHEEL
python_consul2-0.1.5.dist-info/top_level.txt
python_consul2-0.1.5.dist-info/RECORD
