Metadata-Version: 2.1
Name: python-consul2
Version: 0.1.5
Summary: Python client for Consul (http://www.consul.io/)
Home-page: https://github.com/poppyred/python-consul2
Author: yan.gao
Author-email: 373251686@qq.com
License: MIT
Platform: UNKNOWN
Classifier: Development Status :: 3 - Alpha
Classifier: Intended Audience :: Developers
Classifier: License :: OSI Approved :: MIT License
Classifier: Programming Language :: Python :: 2
Classifier: Programming Language :: Python :: 2.7
Classifier: Programming Language :: Python :: 3
Classifier: Programming Language :: Python :: 3.5
Classifier: Programming Language :: Python :: 3.6
Classifier: Programming Language :: Python :: 3.7
Provides-Extra: tornado
Provides-Extra: asyncio
Provides-Extra: twisted
